<?xml version="1.0" encoding="UTF-8"?>

<!--
  Multiple records in a single recordset: in this case, a document and
  several pages. In addition to the minimum required metadata, enough
  additional control data is supplied to map the relationship among the
  records.
-->
<recordset version="1.0">
  <record>
    <type>monograph</type>
    <contributor>oocihm</contributor>
    <key>12469</key>
    <label>Earth's enigmas : a volume of stories /</label>
    <clabel>Earth's enigmas : a volume of stories /</clabel>
    <description/>
    <resource>
      <canonicalUri>http://www.canadiana.org/record/12469</canonicalUri>
    </resource>
  </record>
  <record>
    <type>page</type>
    <contributor>oocihm</contributor>
    <key>12469.0001</key>
    <label>Earth's enigmas : a volume of stories /</label>
    <clabel>technical data sheet</clabel>
    <pkey>12469</pkey>
    <seq>1</seq>
    <description/>
    <resource>
      <canonicalUri>http://www.canadiana.org/view/12469/1</canonicalUri>
    </resource>
  </record>
  <record>
    <type>page</type>
    <contributor>oocihm</contributor>
    <key>12469.0002</key>
    <label>Earth's enigmas : a volume of stories /</label>
    <clabel>blank page</clabel>
    <pkey>12469</pkey>
    <seq>2</seq>
    <description/>
    <resource>
      <canonicalUri>http://www.canadiana.org/view/12469/2</canonicalUri>
    </resource>
  </record>
  <record>
    <type>page</type>
    <contributor>oocihm</contributor>
    <key>12469.0003</key>
    <label>Earth's enigmas : a volume of stories /</label>
    <clabel>title page</clabel>
    <pkey>12469</pkey>
    <seq>3</seq>
    <description/>
    <resource>
      <canonicalUri>http://www.canadiana.org/view/12469/3</canonicalUri>
    </resource>
  </record>
  <record>
    <type>page</type>
    <contributor>oocihm</contributor>
    <key>12469.0004</key>
    <label>Earth's enigmas : a volume of stories /</label>
    <clabel>unnumbered</clabel>
    <pkey>12469</pkey>
    <description/>
    <resource>
      <canonicalUri>http://www.canadiana.org/view/12469/4</canonicalUri>
    </resource>
  </record>
</recordset>
